data_snack_dynamic_entity/__init__.py
data_snack_dynamic_entity/entityTemplates.schema.json
data_snack_dynamic_entity/factory.py
data_snack_dynamic_entity/types.py
data_snack_dynamic_entity/validate.py
data_snack_dynamic_entity/compound_entity/__init__.py
data_snack_dynamic_entity/compound_entity/exceptions.py
data_snack_dynamic_entity/compound_entity/factory.py
data_snack_dynamic_entity/compound_entity/types.py
data_snack_dynamic_entity/simple_entity/__init__.py
data_snack_dynamic_entity/simple_entity/factory.py
data_snack_dynamic_entity/simple_entity/types.py
data_snack_dynamic_entity-0.3.4.dist-info/LICENSE
data_snack_dynamic_entity-0.3.4.dist-info/METADATA
data_snack_dynamic_entity-0.3.4.dist-info/WHEEL
data_snack_dynamic_entity-0.3.4.dist-info/top_level.txt
data_snack_dynamic_entity-0.3.4.dist-info/RECORD
