Metadata-Version: 2.1
Name: data_snack_dynamic_entity
Version: 0.3.4
Home-page: https://github.com/webinterpret-ds/data-snack-dynamic-entity
Author: webinterpret-datascience
Author-email: data-science@webinterpret.com
Project-URL: Bug Tracker, https://github.com/webinterpret-ds/data-snack-dynamic-entity/issues
Classifier: Programming Language :: Python :: 3
Classifier: License :: OSI Approved :: GNU General Public License v3 or later (GPLv3+)
Classifier: Operating System :: OS Independent
Requires-Python: >=3.8
License-File: LICENSE
Requires-Dist: data-snack>=1.0.8
Requires-Dist: jsonschema>=4.17.3
